LICENSE
MANIFEST.in
README.md
setup.cfg
setup.py
test.sh
roca/__init__.py
roca/detect.py
roca/detect_tls.py
roca/tests/__init__.py
roca/tests/test_fingerprint.py
roca/tests/test_tls.py
roca/tests/data/.DS_Store
roca/tests/data/cert01.pem
roca/tests/data/cert02.pem
roca/tests/data/cert03.pem
roca/tests/data/cert04.pem
roca/tests/data/cert05.pem
roca/tests/data/cert06.pem
roca/tests/data/csr03.pem
roca/tests/data/csr05.pem
roca/tests/data/key01.pgp
roca/tests/data/key02.pgp
roca/tests/data/key03.pgp
roca/tests/data/key04.pgp
roca/tests/data/mod01.txt
roca/tests/data/mod02.txt
roca/tests/data/mod03.txt
roca/tests/data/mod04.txt
roca/tests/data/mod05.txt
roca/tests/data/mod06.txt
roca/tests/data/mod07.txt
roca/tests/data/mod08.txt
roca/tests/data/mod09.txt
roca/tests/data/pkcs701.p7s
roca/tests/data/privkey03.pem
roca/tests/data/privkey04.pem
roca/tests/data/privkey05.pem
roca/tests/data/pubkey01.pem
roca/tests/data/pubkey02.pem
roca/tests/data/pubkey03.pem
roca/tests/data/ssh01.pub
roca/tests/data/ssh02.pub
roca/tests/data/ssh03.pub
roca/tests/data/ssh04.pub
roca/tests/data/ssh05.pub
roca/tests/data/ssh06.pub
roca_detect.egg-info/PKG-INFO
roca_detect.egg-info/SOURCES.txt
roca_detect.egg-info/dependency_links.txt
roca_detect.egg-info/entry_points.txt
roca_detect.egg-info/requires.txt
roca_detect.egg-info/top_level.txt