Metadata-Version: 1.2
Name: roca-detect
Version: 1.2.11
Summary: ROCA key detector / fingerprinter tool
Home-page: https://github.com/crocs-muni/roca
Author: Dusan Klinec
Author-email: dusan.klinec@gmail.com
License: MIT
Platform: UNKNOWN
Classifier: Development Status :: 3 - Alpha
Classifier: Intended Audience :: Developers
Classifier: Programming Language :: Python
Classifier: Programming Language :: Python :: 2
Classifier: Programming Language :: Python :: 2.7
Classifier: Programming Language :: Python :: 3
Classifier: Programming Language :: Python :: 3.4
Classifier: Programming Language :: Python :: 3.5
Classifier: Programming Language :: Python :: 3.6
Classifier: Topic :: Security
Requires-Python: >=2.7.10,!=3.0.*,!=3.1.*,!=3.2.*,!=3.3.*
